__init__.py
triangle.py
triangleHelper-0.0.1.dist-info/LICENCE
triangleHelper-0.0.1.dist-info/METADATA
triangleHelper-0.0.1.dist-info/WHEEL
triangleHelper-0.0.1.dist-info/top_level.txt
triangleHelper-0.0.1.dist-info/RECORD
